tests/__init__.py
tests/test_addressable.py
tests/test_cupra.py
tests/test_elements.py
weconnect/__init__.py
weconnect/__version.py
weconnect/addressable.py
weconnect/errors.py
weconnect/fetch.py
weconnect/service.py
weconnect/util.py
weconnect/weconnect.py
weconnect/weconnect_errors.py
weconnect/api/__init__.py
weconnect/api/cupra/__init__.py
weconnect/api/cupra/api.py
weconnect/api/cupra/domain.py
weconnect/api/cupra/auth/__init__.py
weconnect/api/cupra/auth/my_cupra_session.py
weconnect/api/cupra/elements/__init__.py
weconnect/api/cupra/elements/battery_status.py
weconnect/api/cupra/elements/charging_settings.py
weconnect/api/cupra/elements/charging_station.py
weconnect/api/cupra/elements/charging_status.py
weconnect/api/cupra/elements/climatization_settings.py
weconnect/api/cupra/elements/climatization_status.py
weconnect/api/cupra/elements/controls.py
weconnect/api/cupra/elements/engine_state.py
weconnect/api/cupra/elements/enums.py
weconnect/api/cupra/elements/error.py
weconnect/api/cupra/elements/generic_capability.py
weconnect/api/cupra/elements/generic_settings.py
weconnect/api/cupra/elements/odometer_measurement.py
weconnect/api/cupra/elements/parking_position.py
weconnect/api/cupra/elements/vehicle.py
weconnect/api/cupra/elements/helpers/__init__.py
weconnect/api/cupra/elements/helpers/request_tracker.py
weconnect/api/vw/__init__.py
weconnect/api/vw/api.py
weconnect/api/vw/domain.py
weconnect/api/vw/auth/__init__.py
weconnect/api/vw/auth/we_charge_session.py
weconnect/api/vw/auth/we_connect_session.py
weconnect/api/vw/badges/charging.png
weconnect/api/vw/badges/connected.png
weconnect/api/vw/badges/cooling.png
weconnect/api/vw/badges/heating.png
weconnect/api/vw/badges/locked.png
weconnect/api/vw/badges/parking.png
weconnect/api/vw/badges/unlocked.png
weconnect/api/vw/badges/ventilating.png
weconnect/api/vw/badges/warning.png
weconnect/api/vw/elements/__init__.py
weconnect/api/vw/elements/access_status.py
weconnect/api/vw/elements/battery_status.py
weconnect_cupra_one_edition-0.1.4.dist-info/LICENSE
weconnect_cupra_one_edition-0.1.4.dist-info/METADATA
weconnect_cupra_one_edition-0.1.4.dist-info/WHEEL
weconnect_cupra_one_edition-0.1.4.dist-info/top_level.txt
weconnect_cupra_one_edition-0.1.4.dist-info/RECORD
