Metadata-Version: 2.1
Name: weconnect-cupra-one-edition
Version: 0.1.4
Summary: Python API for the Volkswagen WeConnect Services
Home-page: https://github.com/tillsteinbach/WeConnect-python
Author: Till Steinbach
License: MIT
Project-URL: Funding, https://github.com/sponsors/tillsteinbach
Project-URL: Source, https://github.com/tillsteinbach/WeConnect-python
Project-URL: Bug Tracker, https://github.com/tillsteinbach/WeConnect-python/issues
Keywords: weconnect,we connect,carnet,car net,volkswagen,vw,telemetry
Platform: UNKNOWN
Classifier: Development Status :: 3 - Alpha
Classifier: License :: OSI Approved :: MIT License
Classifier: Intended Audience :: Developers
Classifier: Programming Language :: Python :: 3.7
Classifier: Programming Language :: Python :: 3.8
Classifier: Programming Language :: Python :: 3.9
Classifier: Topic :: Software Development :: Libraries
Requires-Python: >=3.7
Requires-Dist: requests (~=2.28.0)
Requires-Dist: oauthlib (~=3.2.0)
Provides-Extra: images
Requires-Dist: pillow (~=9.1.1) ; extra == 'images'
Requires-Dist: ascii-magic (~=1.6.0) ; extra == 'images'
